cirro_api_client/__init__.py
cirro_api_client/cirro_auth.py
cirro_api_client/cirro_client.py
cirro_api_client/v1/__init__.py
cirro_api_client/v1/api/__init__.py
cirro_api_client/v1/api/audit/__init__.py
cirro_api_client/v1/api/audit/get_event.py
cirro_api_client/v1/api/audit/list_events.py
cirro_api_client/v1/api/billing/__init__.py
cirro_api_client/v1/api/billing/create_billing_account.py
cirro_api_client/v1/api/billing/delete_billing_account.py
cirro_api_client/v1/api/billing/get_billing_accounts.py
cirro_api_client/v1/api/billing/update_billing_account.py
cirro_api_client/v1/api/compute_environment/__init__.py
cirro_api_client/v1/api/compute_environment/create_agent.py
cirro_api_client/v1/api/compute_environment/create_compute_environment.py
cirro_api_client/v1/api/compute_environment/delete_agent.py
cirro_api_client/v1/api/compute_environment/delete_compute_environment.py
cirro_api_client/v1/api/compute_environment/get_agents.py
cirro_api_client/v1/api/compute_environment/get_compute_environments.py
cirro_api_client/v1/api/compute_environment/update_agent.py
cirro_api_client/v1/api/compute_environment/update_compute_environment.py
cirro_api_client/v1/api/dashboards/__init__.py
cirro_api_client/v1/api/dashboards/create_dashboard.py
cirro_api_client/v1/api/dashboards/delete_dashboard.py
cirro_api_client/v1/api/dashboards/get_dashboard.py
cirro_api_client/v1/api/dashboards/get_dashboards.py
cirro_api_client/v1/api/dashboards/update_dashboard.py
cirro_api_client/v1/api/datasets/__init__.py
cirro_api_client/v1/api/datasets/delete_dataset.py
cirro_api_client/v1/api/datasets/get_dataset.py
cirro_api_client/v1/api/datasets/get_dataset_manifest.py
cirro_api_client/v1/api/datasets/get_datasets.py
cirro_api_client/v1/api/datasets/get_sample_sheets.py
cirro_api_client/v1/api/datasets/import_public_dataset.py
cirro_api_client/v1/api/datasets/ingest_samples.py
cirro_api_client/v1/api/datasets/regenerate_manifest.py
cirro_api_client/v1/api/datasets/rerun_transform.py
cirro_api_client-1.3.0.dist-info/METADATA
cirro_api_client-1.3.0.dist-info/WHEEL
cirro_api_client-1.3.0.dist-info/RECORD
